nopasaran/__init__.py
nopasaran/__main__.py
nopasaran/decorators.py
nopasaran/http_2_utils.py
nopasaran/http_3_utils.py
nopasaran/utils.py
nopasaran/controllers/__init__.py
nopasaran/controllers/controller.py
nopasaran/controllers/factory.py
nopasaran/controllers/protocol.py
nopasaran/definitions/__init__.py
nopasaran/definitions/commands.py
nopasaran/definitions/control_channel.py
nopasaran/definitions/events.py
nopasaran/definitions/transitions.py
nopasaran/errors/__init__.py
nopasaran/errors/parsing_error.py
nopasaran/interpreters/__init__.py
nopasaran/interpreters/action_interpreter.py
nopasaran/interpreters/condition_interpreter.py
nopasaran/interpreters/interpreter.py
nopasaran/interpreters/transition_interpreter.py
nopasaran/machines/__init__.py
nopasaran/machines/action_queue.py
nopasaran/machines/state_machine.py
nopasaran/parsers/__init__.py
nopasaran/parsers/interpreter_parser.py
nopasaran/parsers/state_machine_parser.py
nopasaran/primitives/__init__.py
nopasaran/primitives/primitives.py
nopasaran/primitives/action_primitives/__init__.py
nopasaran/primitives/action_primitives/action_primitives.py
nopasaran/primitives/action_primitives/certificate_primitives.py
nopasaran/primitives/action_primitives/client_echo_primitives.py
nopasaran/primitives/action_primitives/control_channel_primitives.py
nopasaran/primitives/action_primitives/data_channel_primitives.py
nopasaran/primitives/action_primitives/data_manipulation.py
nopasaran/primitives/action_primitives/dns_primitives.py
nopasaran/primitives/action_primitives/event_primitives.py
nopasaran/primitives/action_primitives/http_1_request_primitives.py
nopasaran/primitives/action_primitives/http_1_response_primitives.py
nopasaran/primitives/action_primitives/http_2_client_primitives.py
nopasaran/primitives/action_primitives/http_2_server_primitives.py
nopasaran/primitives/action_primitives/http_3_client_primitives.py
nopasaran/primitives/action_primitives/http_simple_client_primitives.py
nopasaran-0.2.118.dist-info/LICENSE
nopasaran-0.2.118.dist-info/METADATA
nopasaran-0.2.118.dist-info/WHEEL
nopasaran-0.2.118.dist-info/entry_points.txt
nopasaran-0.2.118.dist-info/top_level.txt
nopasaran-0.2.118.dist-info/RECORD
