Metadata-Version: 2.1
Name: nopasaran
Version: 0.2.118
Summary: NoPASARAN is an advanced network tool designed to detect, fingerprint, and locate network middleboxes in a unified framework.
Home-page: https://github.com/BenIlies/NoPASARAN
Author: Ilies Benhabbour
Author-email: ilies.benhabbour@kaust.edu.sa
License: UNKNOWN
Platform: UNKNOWN
Classifier: Programming Language :: Python :: 3
Classifier: License :: OSI Approved :: GNU General Public License v3 (GPLv3)
Classifier: Operating System :: OS Independent
Requires-Python: >=3.8
Requires-Dist: Twisted
Requires-Dist: pyOpenSSL
Requires-Dist: service-identity
Requires-Dist: psutil
Requires-Dist: scapy
Requires-Dist: h2==4.2.0
Requires-Dist: overload
Requires-Dist: dnspython
Requires-Dist: dnslib
Requires-Dist: aioquic
